yasim/__init__.py
yasim/__main__.py
yasim/_main/__init__.py
yasim/_main/_generate_gene_te_fusion.py
yasim/_main/art.py
yasim/_main/assemble.py
yasim/_main/badread.py
yasim/_main/dtgs.py
yasim/_main/dwgsim.py
yasim/_main/generate_as_events.py
yasim/_main/generate_gene_depth.py
yasim/_main/generate_isoform_depth.py
yasim/_main/generate_isoform_replicates.py
yasim/_main/pbsim.py
yasim/_main/pbsim2.py
yasim/_main/pbsim3.py
yasim/_main/sample_transcript.py
yasim/_main/self_check.py
yasim/_main/transcribe.py
yasim/helper/__init__.py
yasim/helper/as_events.py
yasim/helper/depth.py
yasim/helper/depth_io.py
yasim/helper/frontend.py
yasim/helper/gmm.py
yasim/helper/isoform_depth.py
yasim/helper/llrg.py
yasim/helper/plot_utils.py
yasim/helper/rna_seq.py
yasim/helper/translation_instruction.py
yasim/llrg_adapter/__init__.py
yasim/llrg_adapter/art.py
yasim/llrg_adapter/badread.py
yasim/llrg_adapter/dtgs.py
yasim/llrg_adapter/dwgsim.py
yasim/llrg_adapter/pbsim.py
yasim/llrg_adapter/pbsim2.py
yasim/llrg_adapter/pbsim3.py
yasim/llrg_adapter/pbsim2_dist/.gitignore
yasim/llrg_adapter/pbsim2_dist/P4C2.model
yasim/llrg_adapter/pbsim2_dist/P5C3.model
yasim/llrg_adapter/pbsim2_dist/P6C4.model
yasim/llrg_adapter/pbsim2_dist/R103.model
yasim/llrg_adapter/pbsim2_dist/R94.model
yasim/llrg_adapter/pbsim2_dist/R95.model
yasim/llrg_adapter/pbsim2_dist/Readme.md
yasim/llrg_adapter/pbsim3_dist/.gitignore
yasim/llrg_adapter/pbsim3_dist/ERRHMM-ONT.model
yasim/llrg_adapter/pbsim3_dist/ERRHMM-RSII.model
yasim/llrg_adapter/pbsim3_dist/ERRHMM-SEQUEL.model
yasim/llrg_adapter/pbsim3_dist/QSHMM-ONT.model
yasim/llrg_adapter/pbsim3_dist/QSHMM-RSII.model
yasim/llrg_adapter/pbsim3_dist/Readme.md
yasim/llrg_adapter/pbsim_dist/.gitignore
yasim/llrg_adapter/pbsim_dist/Readme.md
yasim/llrg_adapter/pbsim_dist/model_qc_ccs
yasim/llrg_adapter/pbsim_dist/model_qc_clr
yasim/llrg_adapter/templates/.gitignore
yasim/llrg_adapter/templates/pbsim_xml_template.xml
yasim_scripts/__init__.py
yasim_scripts/__main__.py
yasim-3.2.1.dist-info/Copying.md
yasim-3.2.1.dist-info/License.md
yasim-3.2.1.dist-info/METADATA
yasim-3.2.1.dist-info/WHEEL
yasim-3.2.1.dist-info/top_level.txt
yasim-3.2.1.dist-info/RECORD
