Metadata-Version: 2.1
Name: yasim
Version: 3.2.1
Summary: Yet Another SIMulator for Alternative Splicing Events and Realistic Gene Expression Profile
Author-email: YU Zhejian <Zhejian.23@intl.zju.edu.cn>, SU Yaqi <yaqisu@berkeley.edu>, YUAN Ruihong <Ruihong.19@intl.zju.edu.cn>, CHEN Xinyi <xinyic.21@intl.zju.edu.cn>, "LIU Wanlu (Correspondence)" <wanluliu@intl.zju.edu.cn>
Project-URL: Source, https://github.com/WanluLiuLab/yasim
Project-URL: Documentation, https://labw.org/yasim-docs/
Classifier: Development Status :: 4 - Beta
Classifier: Environment :: Console
Classifier: Intended Audience :: Developers
Classifier: Intended Audience :: Healthcare Industry
Classifier: Intended Audience :: Science/Research
Classifier: License :: OSI Approved :: MIT License
Classifier: Natural Language :: English
Classifier: Operating System :: MacOS :: MacOS X
Classifier: Operating System :: POSIX
Classifier: Programming Language :: Python :: 3 :: Only
Classifier: Programming Language :: Python :: 3.7
Classifier: Programming Language :: Python :: 3.8
Classifier: Programming Language :: Python :: 3.9
Classifier: Programming Language :: Python :: 3.10
Classifier: Programming Language :: Python :: 3.11
Classifier: Programming Language :: Python :: Implementation :: CPython
Classifier: Programming Language :: R
Classifier: Topic :: Scientific/Engineering :: Bio-Informatics
Classifier: Topic :: Utilities
Requires-Python: >=3.7
License-File: License.md
License-File: Copying.md
Requires-Dist: scipy ~=1.7
Requires-Dist: numpy >=1.24
Requires-Dist: tqdm >=4.64
Requires-Dist: tomli-w >=1.0
Requires-Dist: pandas[performance] >=1.4
Requires-Dist: joblib >=1.2
Requires-Dist: labw-utils ==1.0.4
Provides-Extra: pbsim3
Requires-Dist: pysam >=0.20 ; extra == 'pbsim3'
Requires-Dist: jinja2 >=3.1.2 ; extra == 'pbsim3'
